seidart/__init__.py
seidart/.libs/libcpmlfdtd.R6DRHBV6HFROGEJ3N3K3HFI2YSK6X6ND.gfortran-win_amd64.dll
seidart/.libs/liborientsy.46ZIMVLJE5LCA4G2UOFZXRF3CW2ULZMI.gfortran-win_amd64.dll
seidart/fortran/__init__.py
seidart/fortran/cpmlfdtd.cp311-win_amd64.pyd
seidart/fortran/orientsynth.cp311-win_amd64.pyd
seidart/routines/__init__.py
seidart/routines/arraybuild.py
seidart/routines/definitions.py
seidart/routines/materials.py
seidart/routines/orientation_tensor.py
seidart/routines/prjbuild.py
seidart/routines/prjrun.py
seidart/routines/sourcefunction.py
seidart/simulations/__init__.py
seidart/simulations/common_offset.py
seidart/simulations/multioffset.py
seidart/visualization/__init__.py
seidart/visualization/im2anim.py
seidart/visualization/imgen.py
seidart/visualization/implot.py
seidart/visualization/slice25d.py
seidart/visualization/vtkbuild.py
seidart-1.6.0.dist-info/LICENSE.txt
seidart-1.6.0.dist-info/METADATA
seidart-1.6.0.dist-info/WHEEL
seidart-1.6.0.dist-info/top_level.txt
seidart-1.6.0.dist-info/RECORD
