Metadata-Version: 2.1
Name: seidart
Version: 1.6.0
Summary: seidarT is a 2 and 2.5d seismic and electromagnetic modeling suite.
Author-email: Steven Bernsen <steven.bernsen@maine.edu>, Christopher Gerbi <christopher.gerbi@maine.edu>
Maintainer-email: Steven Bernsen <steven.bernsen@maine.edu>, Christopher Gerbi <christopher.gerbi@maine.edu>
License: GNU GENERAL PUBLIC LICENSE
Project-URL: homepage, https://github.com/UMainedynamics/SeidarT
Project-URL: documentation, https://umainedynamics.github.io/SeidarT/index.html
Classifier: Programming Language :: Python :: 3
Classifier: License :: OSI Approved :: GNU Affero General Public License v3
Classifier: Operating System :: OS Independent
Classifier: Framework :: Matplotlib
Classifier: Topic :: Scientific/Engineering :: Physics
Classifier: Intended Audience :: Science/Research
Classifier: Natural Language :: English
Classifier: Development Status :: 4 - Beta
Requires-Python: >=3.11
License-File: LICENSE.txt
Requires-Dist: numpy
Requires-Dist: scipy
Requires-Dist: matplotlib
Requires-Dist: pandas
Requires-Dist: mplstereonet
Requires-Dist: pyevtk
Requires-Dist: glob2
